Metadata-Version: 2.0
Name: odoo10-addon-l10n-es-account-banking-sepa-fsdd
Version: 10.0.1.0.0
Summary: Account Banking Sepa - FSDD (Anticipos de crédito)
Home-page: http://www.comunitea.com
Author: Tecnativa, Odoo Community Association (OCA)
Author-email: support@odoo-community.org
License: AGPL-3
Platform: UNKNOWN
Classifier: Programming Language :: Python :: 2.7
Classifier: Framework :: Odoo
Classifier: License :: OSI Approved :: GNU Affero General Public License v3
Requires-Dist: odoo (<10.1dev,>=10.0)
Requires-Dist: odoo10-addon-account-banking-sepa-direct-debit
